{
  "db_name": "PostgreSQL",
  "query": "\n            INSERT INTO amendment_status_history\n                (id, amendment_id, from_status, to_status, changed_by, remark)\n            VALUES ($1, $2, ($3::TEXT)::amendment_status, ($4::TEXT)::amendment_status, $5, $6)\n            ",
  "describe": {
    "columns": [],
    "parameters": {
      "Left": [
        "Uuid",
        "Uuid",
        "Text",
        "Text",
        "Uuid",
        "Text"
      ]
    },
    "nullable": []
  },
  "hash": "33a28a71259133b41ed397ca528f74613cbcaa3feb37dfbc4dff5b8674ae8a68"
}
